pynba/__init__.py
pynba/core/__init__.py
pynba/core/collector.c
pynba/core/collector.py
pynba/core/collector.so
pynba/core/log.c
pynba/core/log.py
pynba/core/log.so
pynba/core/message.py
pynba/core/reporter.c
pynba/core/reporter.py
pynba/core/reporter.so
pynba/stacked/__init__.py
pynba/stacked/globals.c
pynba/stacked/globals.py
pynba/stacked/globals.so
pynba/stacked/local.c
pynba/stacked/local.py
pynba/stacked/local.so
pynba/util/__init__.py
pynba/util/script.py
pynba/wsgi/__init__.py
pynba/wsgi/ctx.c
pynba/wsgi/ctx.py
pynba/wsgi/ctx.so
pynba/wsgi/middleware.c
pynba/wsgi/middleware.py
pynba/wsgi/middleware.so
pynba-0.5.5.dist-info/DESCRIPTION.rst
pynba-0.5.5.dist-info/METADATA
pynba-0.5.5.dist-info/metadata.json
pynba-0.5.5.dist-info/RECORD
pynba-0.5.5.dist-info/top_level.txt
pynba-0.5.5.dist-info/WHEEL
