Metadata-Version: 2.0
Name: pynba
Version: 0.5.5
Summary: lightweight timers and wsgi middleware to monitor performance in production systems
Home-page: https://github.com/johnnoone/pynba
Author: Xavier Barbosa
Author-email: clint.northwood@gmail.com
License: MIT
Keywords: pinba wsgi monitoring
Platform: UNKNOWN
Classifier: Development Status :: 5 - Production/Stable
Classifier: Intended Audience :: Developers
Classifier: Intended Audience :: Information Technology
Classifier: Intended Audience :: System Administrators
Classifier: License :: OSI Approved :: MIT License
Classifier: Operating System :: OS Independent
Classifier: Programming Language :: Python
Classifier: Programming Language :: Python :: 2.7
Classifier: Programming Language :: Python :: 3.3
Classifier: Programming Language :: Python :: 3.4
Classifier: Programming Language :: Python :: 3.5
Classifier: Programming Language :: Python :: Implementation :: CPython
Classifier: Topic :: Internet :: Log Analysis
Classifier: Topic :: Internet :: WWW/HTTP :: Dynamic Content :: Page Counters
Classifier: Topic :: Internet :: WWW/HTTP :: WSGI :: Middleware
Classifier: Topic :: Software Development :: Libraries
Classifier: Topic :: Software Development :: Libraries :: Python Modules
Classifier: Topic :: System :: Monitoring
Classifier: Topic :: Utilities
Requires-Dist: six
Requires-Dist: enum34; python_version=="2.7"
Requires-Dist: enum34; python_version=="3.2"
Requires-Dist: enum34; python_version=="3.3"
